tap_gmail/__init__.py
tap_gmail/auth.py
tap_gmail/client.py
tap_gmail/schemas/message_list.json
tap_gmail/schemas/messages.json
tap_gmail/streams.py
tap_gmail/tap.py
tap_gmail/tests/__init__.py
tap_gmail/tests/test_core.py
meltanolabs_tap_gmail-0.0.1.dist-info/LICENSE
meltanolabs_tap_gmail-0.0.1.dist-info/METADATA
meltanolabs_tap_gmail-0.0.1.dist-info/WHEEL
meltanolabs_tap_gmail-0.0.1.dist-info/entry_points.txt
meltanolabs_tap_gmail-0.0.1.dist-info/RECORD
